{
  "_metadata": {
    "source": "World Bank Country and Lending Groups",
    "url": "https://datahelpdesk.worldbank.org/knowledgebase/articles/906519",
    "year": 2024,
    "last_updated": "2025-11-11",
    "income_groups": {
      "high-income": "GNI per capita > $13,845",
      "upper-middle-income": "GNI per capita $4,466 - $13,845",
      "lower-middle-income": "GNI per capita $1,136 - $4,465",
      "low-income": "GNI per capita < $1,136"
    }
  },
  "countries": {
    "Afghanistan": { "income_group": "low-income", "region": "South Asia" },
    "Albania": { "income_group": "upper-middle-income", "region": "Europe & Central Asia" },
    "Algeria": { "income_group": "lower-middle-income", "region": "Middle East & North Africa" },
    "Argentina": { "income_group": "upper-middle-income", "region": "Latin America & Caribbean" },
    "Armenia": { "income_group": "upper-middle-income", "region": "Europe & Central Asia" },
    "Australia": { "income_group": "high-income", "region": "East Asia & Pacific" },
    "Austria": { "income_group": "high-income", "region": "Europe & Central Asia" },
    "Azerbaijan": { "income_group": "upper-middle-income", "region": "Europe & Central Asia" },
    "Bahrain": { "income_group": "high-income", "region": "Middle East & North Africa" },
    "Bangladesh": { "income_group": "lower-middle-income", "region": "South Asia" },
    "Belarus": { "income_group": "upper-middle-income", "region": "Europe & Central Asia" },
    "Belgium": { "income_group": "high-income", "region": "Europe & Central Asia" },
    "Benin": { "income_group": "lower-middle-income", "region": "Sub-Saharan Africa" },
    "Bolivia": { "income_group": "lower-middle-income", "region": "Latin America & Caribbean" },
    "Bosnia and Herzegovina": { "income_group": "upper-middle-income", "region": "Europe & Central Asia" },
    "Botswana": { "income_group": "upper-middle-income", "region": "Sub-Saharan Africa" },
    "Brazil": { "income_group": "upper-middle-income", "region": "Latin America & Caribbean" },
    "Bulgaria": { "income_group": "upper-middle-income", "region": "Europe & Central Asia" },
    "Burkina Faso": { "income_group": "low-income", "region": "Sub-Saharan Africa" },
    "Burundi": { "income_group": "low-income", "region": "Sub-Saharan Africa" },
    "Cambodia": { "income_group": "lower-middle-income", "region": "East Asia & Pacific" },
    "Cameroon": { "income_group": "lower-middle-income", "region": "Sub-Saharan Africa" },
    "Canada": { "income_group": "high-income", "region": "North America" },
    "Central African Republic": { "income_group": "low-income", "region": "Sub-Saharan Africa" },
    "Chad": { "income_group": "low-income", "region": "Sub-Saharan Africa" },
    "Chile": { "income_group": "high-income", "region": "Latin America & Caribbean" },
    "China": { "income_group": "upper-middle-income", "region": "East Asia & Pacific" },
    "Colombia": { "income_group": "upper-middle-income", "region": "Latin America & Caribbean" },
    "Congo, Dem. Rep.": { "income_group": "low-income", "region": "Sub-Saharan Africa" },
    "Congo, Rep.": { "income_group": "lower-middle-income", "region": "Sub-Saharan Africa" },
    "Costa Rica": { "income_group": "upper-middle-income", "region": "Latin America & Caribbean" },
    "Croatia": { "income_group": "high-income", "region": "Europe & Central Asia" },
    "Cuba": { "income_group": "upper-middle-income", "region": "Latin America & Caribbean" },
    "Cyprus": { "income_group": "high-income", "region": "Europe & Central Asia" },
    "Czech Republic": { "income_group": "high-income", "region": "Europe & Central Asia" },
    "Denmark": { "income_group": "high-income", "region": "Europe & Central Asia" },
    "Dominican Republic": { "income_group": "upper-middle-income", "region": "Latin America & Caribbean" },
    "Ecuador": { "income_group": "upper-middle-income", "region": "Latin America & Caribbean" },
    "Egypt": { "income_group": "lower-middle-income", "region": "Middle East & North Africa" },
    "El Salvador": { "income_group": "lower-middle-income", "region": "Latin America & Caribbean" },
    "Estonia": { "income_group": "high-income", "region": "Europe & Central Asia" },
    "Ethiopia": { "income_group": "low-income", "region": "Sub-Saharan Africa" },
    "Finland": { "income_group": "high-income", "region": "Europe & Central Asia" },
    "France": { "income_group": "high-income", "region": "Europe & Central Asia" },
    "Georgia": { "income_group": "upper-middle-income", "region": "Europe & Central Asia" },
    "Germany": { "income_group": "high-income", "region": "Europe & Central Asia" },
    "Ghana": { "income_group": "lower-middle-income", "region": "Sub-Saharan Africa" },
    "Greece": { "income_group": "high-income", "region": "Europe & Central Asia" },
    "Guatemala": { "income_group": "upper-middle-income", "region": "Latin America & Caribbean" },
    "Guinea": { "income_group": "low-income", "region": "Sub-Saharan Africa" },
    "Haiti": { "income_group": "lower-middle-income", "region": "Latin America & Caribbean" },
    "Honduras": { "income_group": "lower-middle-income", "region": "Latin America & Caribbean" },
    "Hong Kong": { "income_group": "high-income", "region": "East Asia & Pacific" },
    "Hungary": { "income_group": "high-income", "region": "Europe & Central Asia" },
    "Iceland": { "income_group": "high-income", "region": "Europe & Central Asia" },
    "India": { "income_group": "lower-middle-income", "region": "South Asia" },
    "Indonesia": { "income_group": "lower-middle-income", "region": "East Asia & Pacific" },
    "Iran": { "income_group": "lower-middle-income", "region": "Middle East & North Africa" },
    "Iraq": { "income_group": "upper-middle-income", "region": "Middle East & North Africa" },
    "Ireland": { "income_group": "high-income", "region": "Europe & Central Asia" },
    "Israel": { "income_group": "high-income", "region": "Middle East & North Africa" },
    "Italy": { "income_group": "high-income", "region": "Europe & Central Asia" },
    "Jamaica": { "income_group": "upper-middle-income", "region": "Latin America & Caribbean" },
    "Japan": { "income_group": "high-income", "region": "East Asia & Pacific" },
    "Jordan": { "income_group": "lower-middle-income", "region": "Middle East & North Africa" },
    "Kazakhstan": { "income_group": "upper-middle-income", "region": "Europe & Central Asia" },
    "Kenya": { "income_group": "lower-middle-income", "region": "Sub-Saharan Africa" },
    "Korea, South": { "income_group": "high-income", "region": "East Asia & Pacific" },
    "Kuwait": { "income_group": "high-income", "region": "Middle East & North Africa" },
    "Kyrgyzstan": { "income_group": "lower-middle-income", "region": "Europe & Central Asia" },
    "Latvia": { "income_group": "high-income", "region": "Europe & Central Asia" },
    "Lebanon": { "income_group": "upper-middle-income", "region": "Middle East & North Africa" },
    "Liberia": { "income_group": "low-income", "region": "Sub-Saharan Africa" },
    "Libya": { "income_group": "upper-middle-income", "region": "Middle East & North Africa" },
    "Lithuania": { "income_group": "high-income", "region": "Europe & Central Asia" },
    "Luxembourg": { "income_group": "high-income", "region": "Europe & Central Asia" },
    "Madagascar": { "income_group": "low-income", "region": "Sub-Saharan Africa" },
    "Malawi": { "income_group": "low-income", "region": "Sub-Saharan Africa" },
    "Malaysia": { "income_group": "upper-middle-income", "region": "East Asia & Pacific" },
    "Mali": { "income_group": "low-income", "region": "Sub-Saharan Africa" },
    "Mexico": { "income_group": "upper-middle-income", "region": "Latin America & Caribbean" },
    "Morocco": { "income_group": "lower-middle-income", "region": "Middle East & North Africa" },
    "Mozambique": { "income_group": "low-income", "region": "Sub-Saharan Africa" },
    "Myanmar": { "income_group": "lower-middle-income", "region": "East Asia & Pacific" },
    "Nepal": { "income_group": "lower-middle-income", "region": "South Asia" },
    "Netherlands": { "income_group": "high-income", "region": "Europe & Central Asia" },
    "New Zealand": { "income_group": "high-income", "region": "East Asia & Pacific" },
    "Nicaragua": { "income_group": "lower-middle-income", "region": "Latin America & Caribbean" },
    "Niger": { "income_group": "low-income", "region": "Sub-Saharan Africa" },
    "Nigeria": { "income_group": "lower-middle-income", "region": "Sub-Saharan Africa" },
    "North Macedonia": { "income_group": "upper-middle-income", "region": "Europe & Central Asia" },
    "Norway": { "income_group": "high-income", "region": "Europe & Central Asia" },
    "Pakistan": { "income_group": "lower-middle-income", "region": "South Asia" },
    "Panama": { "income_group": "high-income", "region": "Latin America & Caribbean" },
    "Paraguay": { "income_group": "upper-middle-income", "region": "Latin America & Caribbean" },
    "Peru": { "income_group": "upper-middle-income", "region": "Latin America & Caribbean" },
    "Philippines": { "income_group": "lower-middle-income", "region": "East Asia & Pacific" },
    "Poland": { "income_group": "high-income", "region": "Europe & Central Asia" },
    "Portugal": { "income_group": "high-income", "region": "Europe & Central Asia" },
    "Qatar": { "income_group": "high-income", "region": "Middle East & North Africa" },
    "Romania": { "income_group": "high-income", "region": "Europe & Central Asia" },
    "Russia": { "income_group": "upper-middle-income", "region": "Europe & Central Asia" },
    "Rwanda": { "income_group": "low-income", "region": "Sub-Saharan Africa" },
    "Saudi Arabia": { "income_group": "high-income", "region": "Middle East & North Africa" },
    "Senegal": { "income_group": "lower-middle-income", "region": "Sub-Saharan Africa" },
    "Serbia": { "income_group": "upper-middle-income", "region": "Europe & Central Asia" },
    "Sierra Leone": { "income_group": "low-income", "region": "Sub-Saharan Africa" },
    "Singapore": { "income_group": "high-income", "region": "East Asia & Pacific" },
    "Slovakia": { "income_group": "high-income", "region": "Europe & Central Asia" },
    "Slovenia": { "income_group": "high-income", "region": "Europe & Central Asia" },
    "Somalia": { "income_group": "low-income", "region": "Sub-Saharan Africa" },
    "South Africa": { "income_group": "upper-middle-income", "region": "Sub-Saharan Africa" },
    "South Sudan": { "income_group": "low-income", "region": "Sub-Saharan Africa" },
    "Spain": { "income_group": "high-income", "region": "Europe & Central Asia" },
    "Sri Lanka": { "income_group": "lower-middle-income", "region": "South Asia" },
    "Sudan": { "income_group": "low-income", "region": "Sub-Saharan Africa" },
    "Sweden": { "income_group": "high-income", "region": "Europe & Central Asia" },
    "Switzerland": { "income_group": "high-income", "region": "Europe & Central Asia" },
    "Syria": { "income_group": "low-income", "region": "Middle East & North Africa" },
    "Taiwan": { "income_group": "high-income", "region": "East Asia & Pacific" },
    "Tajikistan": { "income_group": "lower-middle-income", "region": "Europe & Central Asia" },
    "Tanzania": { "income_group": "lower-middle-income", "region": "Sub-Saharan Africa" },
    "Thailand": { "income_group": "upper-middle-income", "region": "East Asia & Pacific" },
    "Togo": { "income_group": "low-income", "region": "Sub-Saharan Africa" },
    "Tunisia": { "income_group": "lower-middle-income", "region": "Middle East & North Africa" },
    "Turkey": { "income_group": "upper-middle-income", "region": "Europe & Central Asia" },
    "Turkmenistan": { "income_group": "upper-middle-income", "region": "Europe & Central Asia" },
    "Uganda": { "income_group": "low-income", "region": "Sub-Saharan Africa" },
    "Ukraine": { "income_group": "lower-middle-income", "region": "Europe & Central Asia" },
    "United Arab Emirates": { "income_group": "high-income", "region": "Middle East & North Africa" },
    "United Kingdom": { "income_group": "high-income", "region": "Europe & Central Asia" },
    "United States": { "income_group": "high-income", "region": "North America" },
    "Uruguay": { "income_group": "high-income", "region": "Latin America & Caribbean" },
    "Uzbekistan": { "income_group": "lower-middle-income", "region": "Europe & Central Asia" },
    "Venezuela": { "income_group": "upper-middle-income", "region": "Latin America & Caribbean" },
    "Vietnam": { "income_group": "lower-middle-income", "region": "East Asia & Pacific" },
    "Yemen": { "income_group": "low-income", "region": "Middle East & North Africa" },
    "Zambia": { "income_group": "lower-middle-income", "region": "Sub-Saharan Africa" },
    "Zimbabwe": { "income_group": "lower-middle-income", "region": "Sub-Saharan Africa" }
  },
  "popular_countries": [
    "United States",
    "China",
    "India",
    "United Kingdom",
    "Germany",
    "France",
    "Japan",
    "Brazil",
    "Canada",
    "Australia",
    "Mexico",
    "South Africa",
    "Nigeria",
    "Indonesia",
    "Russia"
  ]
}
